strangeworks_extensions/__init__.py
strangeworks_extensions/extensions.py
strangeworks_extensions/products.py
strangeworks_extensions/utils.py
strangeworks_extensions/plugins/__init__.py
strangeworks_extensions/plugins/instance.py
strangeworks_extensions/plugins/instrumentation.py
strangeworks_extensions/plugins/plugin.py
strangeworks_extensions/plugins/runtime.py
strangeworks_extensions/plugins/serverless.py
strangeworks_extensions/plugins/types.py
strangeworks_extensions/plugins/requests/__init__.py
strangeworks_extensions/plugins/requests/plugin.py
strangeworks_extensions/plugins/requests/proxy.py
strangeworks_extensions/plugins/requests/redirect.py
strangeworks_extensions/sdk/__init__.py
strangeworks_extensions/sdk/_cfg_file.py
strangeworks_extensions/sdk/_gql.py
strangeworks_extensions/sdk/_resource.py
strangeworks_extensions/sdk/platform.py
strangeworks_extensions/serverless/__init__.py
strangeworks_extensions/serverless/decorator.py
strangeworks_extensions/serverless/types.py
strangeworks_extensions/types/__init__.py
strangeworks_extensions/types/_artifact.py
strangeworks_extensions/types/_services.py
strangeworks_extensions/types/events.py
strangeworks_extensions/types/plugins.py
strangeworks_extensions-0.8.0.dist-info/METADATA
strangeworks_extensions-0.8.0.dist-info/WHEEL
strangeworks_extensions-0.8.0.dist-info/entry_points.txt
strangeworks_extensions-0.8.0.dist-info/RECORD
