Metadata-Version: 2.4
Name: strangeworks-extensions
Version: 0.8.0
Summary: Shared code for SDK Extensions
Author-email: Strange Devs <hello@strangeworks.com>
Requires-Python: >=3.11
Requires-Dist: strangeworks-core>=0.5.1
